README.md
setup.py
pushradar/__init__.py
pushradar/pushradar.py
pushradar.egg-info/PKG-INFO
pushradar.egg-info/SOURCES.txt
pushradar.egg-info/dependency_links.txt
pushradar.egg-info/requires.txt
pushradar.egg-info/top_level.txt